setup.py
hshshshs/__init__.py
hshshshs/cFunction.py
hshshshs.egg-info/PKG-INFO
hshshshs.egg-info/SOURCES.txt
hshshshs.egg-info/dependency_links.txt
hshshshs.egg-info/requires.txt
hshshshs.egg-info/top_level.txt