Metadata-Version: 2.1
Name: hshshshs
Version: 0.1.0
Summary: math function
Home-page: http://github.com/kimhansu/hshshshs
Author: kimhansu
Author-email: gimhansu@naver.com
License: MIT
Keywords: calendar,isoweek,listsum
Platform: UNKNOWN
